ida_trace_analysis_helper/__init__.py
ida_trace_analysis_helper/trace_file_analysis.py
tests/__init__.py
ida_trace_analysis_helper-0.0.2.dist-info/METADATA
ida_trace_analysis_helper-0.0.2.dist-info/WHEEL
ida_trace_analysis_helper-0.0.2.dist-info/top_level.txt
ida_trace_analysis_helper-0.0.2.dist-info/RECORD
