Metadata-Version: 2.1
Name: ida-trace-analysis-helper
Version: 0.0.2
Summary: parse the ida trace file and track the register from
Home-page: https://github.com/BeyondMark/IdaTraceAnalysisHelper
Author: beyond_mark
Author-email: luck.yangbo@gmail.com
License: UNKNOWN
Platform: UNKNOWN
Classifier: Programming Language :: Python :: 3
Classifier: License :: OSI Approved :: MIT License
Classifier: Operating System :: OS Independent
Requires-Python: >=3.7
